task2/f1_fsm.sv
module f1_fsm #(
    parameter   WIDTH = 8
)(
    input   logic               clk,        // clock
    input   logic               rst,        // reset
    input   logic               en,         // enable
    output  logic [WIDTH-1:0]   data_out    // data out
);

    // Define our states
    typedef enum {S0, S1, S2, S3, S4, S5, S6, S7, S8} my_state;
    my_state current_state, next_state;

    // state registers
    always_ff @(posedge clk, posedge rst)
        if (rst)        current_state <= S0;
        else            current_state <= next_state;

    // next state logic
    always_comb
        case (current_state)
            S0:         if (en == 1)    next_state = S1;
                        else            next_state = current_state;
            S1:         if (en == 1)    next_state = S2;
                        else            next_state = current_state;
            S2:         if (en == 1)    next_state = S3;
                        else            next_state = current_state;
            S3:         if (en == 1)    next_state = S4;
                        else            next_state = current_state;
            S4:         if (en == 1)    next_state = S5;
                        else            next_state = current_state;
            S5:         if (en == 1)    next_state = S6;
                        else            next_state = current_state;
            S6:         if (en == 1)    next_state = S7;
                        else            next_state = current_state;
            S7:         if (en == 1)    next_state = S8;
                        else            next_state = current_state;
            S8:         if (en == 1)    next_state = S0;
                        else            next_state = current_state;
            default: next_state = S0;
        endcase

    // output logic
    always @(posedge clk)
        case (current_state)
            S0:         assign data_out = 8'b0;
            S1:         assign data_out = 8'b1;
            S2:         assign data_out = 8'b11;
            S3:         assign data_out = 8'b111;
            S4:         assign data_out = 8'b1111;
            S5:         assign data_out = 8'b11111;
            S6:         assign data_out = 8'b111111;
            S7:         assign data_out = 8'b1111111;
            S8:         assign data_out = 8'b11111111;
            default:    assign data_out = 8'b0;
        endcase
endmodule

task2/f1_fsm.vcd
$version Generated by VerilatedVcd $end
$date Thu Nov  3 23:32:37 2022 $end
$timescale 1ps $end

 $scope module TOP $end
  $var wire  1 # clk $end
  $var wire  8 & data_out [7:0] $end
  $var wire  1 % en $end
  $var wire  1 $ rst $end
  $scope module f1_fsm $end
   $var wire 32 ) WIDTH [31:0] $end
   $var wire  1 # clk $end
   $var wire  9 ' current_state [8:0] $end
   $var wire  8 & data_out [7:0] $end
   $var wire  1 % en $end
   $var wire  9 ( next_state [8:0] $end
   $var wire  1 $ rst $end
  $upscope $end
 $upscope $end
$enddefinitions $end


#0
1#
0$
0%
b00000000 &
b000000000 '
b000000000 (
b00000000000000000000000000001000 )
#1
0#
#2
1#
1$
#3
0#
#4
1#
#5
0#
#6
1#
0$
#7
0#
#8
1#
#9
0#
#10
1#
#11
0#
#12
1#
#13
0#
#14
1#
#15
0#
#16
1#
#17
0#
#18
1#
#19
0#
#20
1#
#21
0#
#22
1#
#23
0#
#24
1#
#25
0#
#26
1#
#27
0#
#28
1#
#29
0#
#30
1#
#31
0#
#32
1#
#33
0#
#34
1#
#35
0#
#36
1#
#37
0#
#38
1#
#39
0#
#40
1#
#41
0#
#42
1#
#43
0#
#44
1#
#45
0#
#46
1#
#47
0#
#48
1#
#49
0#
#50
1#
#51
0#
#52
1#
#53
0#
#54
1#
#55
0#
#56
1#
#57
0#
#58
1#
#59
0#
#60
1#
#61
0#
#62
1#
#63
0#
#64
1#
#65
0#
#66
1#
#67
0#
#68
1#
#69
0#
#70
1#
#71
0#
#72
1#
#73
0#
#74
1#
#75
0#
#76
1#
#77
0#
#78
1#
#79
0#
#80
1#
#81
0#
#82
1#
#83
0#
#84
1#
#85
0#
#86
1#
#87
0#
#88
1#
#89
0#
#90
1#
#91
0#
#92
1#
#93
0#
#94
1#
#95
0#
#96
1#
#97
0#
#98
1#
#99
0#
#100
1#
#101
0#
#102
1#
#103
0#
#104
1#
#105
0#
#106
1#
#107
0#
#108
1#
#109
0#
#110
1#
#111
0#
#112
1#
#113
0#
#114
1#
#115
0#
#116
1#
#117
0#
#118
1#
#119
0#
#120
1#
#121
0#
#122
1#
#123
0#
#124
1#
#125
0#
#126
1#
#127
0#
#128
1#
#129
0#
#130
1#
#131
0#
#132
1#
#133
0#
#134
1#
#135
0#
#136
1#
#137
0#
#138
1#
#139
0#
#140
1#
#141
0#
#142
1#
#143
0#
#144
1#
#145
0#
#146
1#
#147
0#
#148
1#
#149
0#
#150
1#
#151
0#
#152
1#
#153
0#
#154
1#
#155
0#
#156
1#
#157
0#
#158
1#
#159
0#
#160
1#
#161
0#
#162
1#
#163
0#
#164
1#
#165
0#
#166
1#
#167
0#
#168
1#
#169
0#
#170
1#
#171
0#
#172
1#
#173
0#
#174
1#
#175
0#
#176
1#
#177
0#
#178
1#
#179
0#
#180
1#
#181
0#
#182
1#
#183
0#
#184
1#
#185
0#
#186
1#
#187
0#
#188
1#
#189
0#
#190
1#
#191
0#
#192
1#
#193
0#
#194
1#
#195
0#
#196
1#
#197
0#
#198
1#
#199
0#
#200
1#
#201
0#
#202
1#
#203
0#
#204
1#
#205
0#
#206
1#
#207
0#
#208
1#
#209
0#
#210
1#
#211
0#
#212
1#
#213
0#
#214
1#
#215
0#
#216
1#
#217
0#
#218
1#
#219
0#
#220
1#
#221
0#
#222
1#
#223
0#
#224
1#
#225
0#
#226
1#
#227
0#
#228
1#
#229
0#
#230
1#
#231
0#
#232
1#
#233
0#
#234
1#
#235
0#
#236
1#
#237
0#
#238
1#
#239
0#
#240
1#
#241
0#
#242
1#
#243
0#
#244
1#
#245
0#
#246
1#
#247
0#
#248
1#
#249
0#
#250
1#
#251
0#
#252
1#
#253
0#
#254
1#
#255
0#
#256
1#
#257
0#
#258
1#
#259
0#
#260
1#
#261
0#
#262
1#
#263
0#
#264
1#
#265
0#
#266
1#
#267
0#
#268
1#
#269
0#
#270
1#
#271
0#
#272
1#
#273
0#
#274
1#
#275
0#
#276
1#
#277
0#
#278
1#
#279
0#
#280
1#
#281
0#
#282
1#
#283
0#
#284
1#
#285
0#
#286
1#
#287
0#
#288
1#
#289
0#
#290
1#
#291
0#
#292
1#
#293
0#
#294
1#
#295
0#
#296
1#
#297
0#
#298
1#
#299
0#
#300
1#
#301
0#
#302
1#
#303
0#
#304
1#
#305
0#
#306
1#
#307
0#
#308
1#
#309
0#
#310
1#
#311
0#
#312
1#
#313
0#
#314
1#
#315
0#
#316
1#
#317
0#
#318
1#
#319
0#
#320
1#
#321
0#
#322
1#
#323
0#
#324
1#
#325
0#
#326
1#
#327
0#
#328
1#
#329
0#
#330
1#
#331
0#
#332
1#
#333
0#
#334
1#
#335
0#
#336
1#
#337
0#
#338
1#
#339
0#
#340
1#
#341
0#
#342
1#
#343
0#
#344
1#
#345
0#
#346
1#
#347
0#
#348
1#
#349
0#
#350
1#
#351
0#
#352
1#
#353
0#
#354
1#
#355
0#
#356
1#
#357
0#
#358
1#
#359
0#
#360
1#
#361
0#
#362
1#
#363
0#
#364
1#
#365
0#
#366
1#
#367
0#
#368
1#
#369
0#
#370
1#
#371
0#
#372
1#
#373
0#
#374
1#
#375
0#
#376
1#
#377
0#
#378
1#
#379
0#
#380
1#
#381
0#
#382
1#
#383
0#
#384
1#
#385
0#
#386
1#
#387
0#
#388
1#
#389
0#
#390
1#
#391
0#
#392
1#
#393
0#
#394
1#
#395
0#
#396
1#
#397
0#
#398
1#
#399
0#
#400
1#
#401
0#
#402
1#
#403
0#
#404
1#
#405
0#
#406
1#
#407
0#
#408
1#
#409
0#
#410
1#
#411
0#
#412
1#
#413
0#
#414
1#
#415
0#
#416
1#
#417
0#
#418
1#
#419
0#
#420
1#
#421
0#
#422
1#
#423
0#
#424
1#
#425
0#
#426
1#
#427
0#
#428
1#
#429
0#
#430
1#
#431
0#
#432
1#
#433
0#
#434
1#
#435
0#
#436
1#
#437
0#
#438
1#
#439
0#
#440
1#
#441
0#
#442
1#
#443
0#
#444
1#
#445
0#
#446
1#
#447
0#
#448
1#
#449
0#
#450
1#
#451
0#
#452
1#
#453
0#
#454
1#
#455
0#
#456
1#
#457
0#
#458
1#
1%
#459
0#
b000000001 (
#460
1#
0%
b000000001 '
b000000010 (
#461
0#
b000000001 (
#462
1#
b00000001 &
